setup.cfg
setup.py
code_monkey/__init__.py
code_monkey/change.py
code_monkey/edit.py
code_monkey/end_detection.py
code_monkey/format.py
code_monkey/node_query.py
code_monkey/utils.py
code_monkey.egg-info/PKG-INFO
code_monkey.egg-info/SOURCES.txt
code_monkey.egg-info/dependency_links.txt
code_monkey.egg-info/pbr.json
code_monkey.egg-info/requires.txt
code_monkey.egg-info/top_level.txt