Metadata-Version: 1.1
Name: code-monkey
Version: 0.0.3
Summary: A Python refactoring/static analysis tool
Home-page: https://github.com/ForSpareParts/code_monkey
Author: David Jackson
Author-email: altmail@jackson-wallace.net
License: MIT
Keywords: development code_generation static_analysis
Platform: UNKNOWN
Classifier: Development Status :: 3 - Alpha
Classifier: Intended Audience :: Developers
Classifier: Topic :: Software Development :: Code Generators
Classifier: License :: OSI Approved :: MIT License
Classifier: Programming Language :: Python :: 2
Classifier: Programming Language :: Python :: 2.6
Classifier: Programming Language :: Python :: 2.7
